README.md
setup.py
libccv/__init__.py
libccv/hough_detect_line.py
libccv/img_brightness.py
libccv/img_fisheye_mask.py
libccv/img_match_graph.py
libccv/img_statistic.py
libccv/img_to_bin.py
libccv/imtools.py
libccv/pil_demo.py
libccv/pylab_demo.py
libccv.egg-info/PKG-INFO
libccv.egg-info/SOURCES.txt
libccv.egg-info/dependency_links.txt
libccv.egg-info/entry_points.txt
libccv.egg-info/requires.txt
libccv.egg-info/top_level.txt
libccv/fft/__init__.py
libccv/fft/fft_denoise_image.py
libccv/fft/fft_fde.py
libccv/fft/fft_ocv_01.py
libccv/fft/fft_ocv_02.py
libccv/fft/fft_ocv_hpf.py